terminal_text_style/__init__.py
terminal_text_style/style.py
terminal_text_style/tempCodeRunnerFile.py
terminal_text_style-0.0.2.dist-info/licenses/LICENSE
terminal_text_style-0.0.2.dist-info/METADATA
terminal_text_style-0.0.2.dist-info/WHEEL
terminal_text_style-0.0.2.dist-info/top_level.txt
terminal_text_style-0.0.2.dist-info/RECORD
