Metadata-Version: 2.4
Name: terminal_text_style
Version: 0.0.2
Summary: Style texts in the terminal with colors, backgrounds and styles in an easy way.
Home-page: https://github.com/Victor-f-Paiva/terminal-text-style.git
Author: Victor Paiva
Author-email: victor_eduardof@hotmail.com
Keywords: terminal style color ansi cli
Classifier: Programming Language :: Python :: 3
Classifier: License :: OSI Approved :: MIT License
Classifier: Operating System :: OS Independent
Requires-Python: >=3.7
License-File: LICENSE
Dynamic: author
Dynamic: author-email
Dynamic: classifier
Dynamic: description-content-type
Dynamic: home-page
Dynamic: keywords
Dynamic: license-file
Dynamic: requires-python
Dynamic: summary
